kube_copilot/__init__.py
kube_copilot/agent.py
kube_copilot/cli.py
kube_copilot/kubeconfig.py
kube_copilot/labeler.py
kube_copilot/output.py
kube_copilot/prompts.py
kube_copilot/python.py
kube_copilot/shell.py
kube_copilot/st_callable_util.py
kube_copilot/utils.py
kube_copilot-0.2.1.dist-info/LICENSE
kube_copilot-0.2.1.dist-info/METADATA
kube_copilot-0.2.1.dist-info/WHEEL
kube_copilot-0.2.1.dist-info/entry_points.txt
kube_copilot-0.2.1.dist-info/RECORD
