Metadata-Version: 2.3
Name: kube-copilot
Version: 0.2.1
Summary: Kubernetes Copilot
Keywords: kubernetes,copilot,openai,chatgpt,ai,agentic
Author: Pengfei Ni
Author-email: feiskyer@gmail.com
Requires-Python: >=3.12,<4
Classifier: Programming Language :: Python :: 3
Classifier: Programming Language :: Python :: 3.12
Classifier: Programming Language :: Python :: 3.13
Requires-Dist: click (>=8.2.1,<9.0.0)
Requires-Dist: faiss-cpu (>=1.11.0,<2.0.0)
Requires-Dist: google-api-python-client (>=2.176.0)
Requires-Dist: kubernetes (>=33.1.0)
Requires-Dist: langchain-experimental (>=0.3.4,<0.4.0)
Requires-Dist: langchain-google-community (>=2.0.7,<3.0.0)
Requires-Dist: langchain-openai (>=0.3.27,<0.4.0)
Requires-Dist: langgraph (>=0.5.2,<0.6.0)
Requires-Dist: lark (>=1.2.2,<2.0.0)
Requires-Dist: openai (>=1.95.1,<2.0.0)
Requires-Dist: python-dotenv (>=1.1.1,<2.0.0)
Requires-Dist: requests (>=2.32.4,<3.0.0)
Requires-Dist: streamlit (>=1.46.1,<2.0.0)
Requires-Dist: tiktoken (>=0.9.0,<0.10.0)
Project-URL: Homepage, https://github.com/feiskyer/kube-copilot
Project-URL: Repository, https://github.com/feiskyer/kube-copilot
